locustodoorpc/__init__.py
locustodoorpc/client.py
locustodoorpc-0.0.4.dist-info/METADATA
locustodoorpc-0.0.4.dist-info/WHEEL
locustodoorpc-0.0.4.dist-info/top_level.txt
locustodoorpc-0.0.4.dist-info/RECORD
