Metadata-Version: 2.1
Name: locustodoorpc
Version: 0.0.4
Summary: Locust custom client: odoorpc
Home-page: https://github.com/camptocamp/locustodoorpc
Author: Camptocamp
Author-email: info@camptocamp.com
License: LGPLv3+
Platform: UNKNOWN
Classifier: Development Status :: 3 - Alpha
Classifier: Intended Audience :: Developers
Classifier: Natural Language :: English
Classifier: License :: OSI Approved :: GNU Lesser General Public License v3 or later (LGPLv3+)
Classifier: Programming Language :: Python
Classifier: Programming Language :: Python :: 3
Classifier: Programming Language :: Python :: 3 :: Only
Classifier: Programming Language :: Python :: 3.8
Classifier: Programming Language :: Python :: Implementation :: CPython
Requires-Dist: locust (>=2.13.0)
Requires-Dist: odoorpc (>=0.9.0)
